requests_viewer/__init__.py
requests_viewer/image.py
requests_viewer/js.py
requests_viewer/main.py
requests_viewer/web.py
requests_viewer/web_compat.py
requests_viewer/.mypy_cache/.gitignore
requests_viewer/.mypy_cache/CACHEDIR.TAG
requests_viewer/.mypy_cache/3.10/@plugins_snapshot.json
requests_viewer/.mypy_cache/3.10/__future__.data.json
requests_viewer/.mypy_cache/3.10/__future__.meta.json
requests_viewer/.mypy_cache/3.10/_ast.data.json
requests_viewer/.mypy_cache/3.10/_ast.meta.json
requests_viewer/.mypy_cache/3.10/_bisect.data.json
requests_viewer/.mypy_cache/3.10/_bisect.meta.json
requests_viewer/.mypy_cache/3.10/_codecs.data.json
requests_viewer/.mypy_cache/3.10/_codecs.meta.json
requests_viewer/.mypy_cache/3.10/_collections_abc.data.json
requests_viewer/.mypy_cache/3.10/_collections_abc.meta.json
requests_viewer/.mypy_cache/3.10/_socket.data.json
requests_viewer/.mypy_cache/3.10/_socket.meta.json
requests_viewer/.mypy_cache/3.10/_stat.data.json
requests_viewer/.mypy_cache/3.10/_stat.meta.json
requests_viewer/.mypy_cache/3.10/_thread.data.json
requests_viewer/.mypy_cache/3.10/_thread.meta.json
requests_viewer/.mypy_cache/3.10/_warnings.data.json
requests_viewer/.mypy_cache/3.10/_warnings.meta.json
requests_viewer/.mypy_cache/3.10/abc.data.json
requests_viewer/.mypy_cache/3.10/abc.meta.json
requests_viewer/.mypy_cache/3.10/array.data.json
requests_viewer/.mypy_cache/3.10/array.meta.json
requests_viewer/.mypy_cache/3.10/base64.data.json
requests_viewer/.mypy_cache/3.10/base64.meta.json
requests_viewer/.mypy_cache/3.10/bisect.data.json
requests_viewer/.mypy_cache/3.10/bisect.meta.json
requests_viewer/.mypy_cache/3.10/builtins.data.json
requests_viewer/.mypy_cache/3.10/builtins.meta.json
requests_viewer/.mypy_cache/3.10/codecs.data.json
requests_viewer/.mypy_cache/3.10/codecs.meta.json
requests_viewer/.mypy_cache/3.10/contextlib.data.json
requests_viewer/.mypy_cache/3.10/contextlib.meta.json
requests_viewer/.mypy_cache/3.10/datetime.data.json
requests_viewer-0.1.0.dist-info/METADATA
requests_viewer-0.1.0.dist-info/WHEEL
requests_viewer-0.1.0.dist-info/top_level.txt
requests_viewer-0.1.0.dist-info/RECORD
