Metadata-Version: 2.1
Name: requests-viewer
Version: 0.1.0
Summary: requests_viewer!
Home-page: https://github.com/kootenpv/requests_viewer
Author: Pascal van Kooten
Author-email: kootenpv@gmail.com
License: MIT
Platform: any
Requires-Dist: requests
Requires-Dist: lxml
Requires-Dist: beatifulsoup4
Provides-Extra: fancy
Requires-Dist: tldextract ; extra == 'fancy'
